classyenv/__init__.py
classyenv/base_class.py
classyenv/descriptor.py
classyenv/errors.py
classy_env-1.3.1.dist-info/LICENSE
classy_env-1.3.1.dist-info/METADATA
classy_env-1.3.1.dist-info/WHEEL
classy_env-1.3.1.dist-info/top_level.txt
classy_env-1.3.1.dist-info/RECORD
