Metadata-Version: 2.1
Name: classy-env
Version: 1.3.1
Summary: Classy Env is a lightweight python package for managing environment variables in OOP way.
Home-page: https://github.com/mateusz-meksula/classy-env/
Author: Mateusz Meksuła
License: MIT
Classifier: Intended Audience :: Developers
Classifier: Programming Language :: Python :: 3
Classifier: Programming Language :: Python :: 3.11
Classifier: Programming Language :: Python :: 3.12
Classifier: Topic :: Utilities
Requires-Python: >=3.11
License-File: LICENSE
